README.md
pyproject.toml
setup.cfg
setup.py
thinmam/MOX.py
thinmam/SS.py
thinmam/__init__.py
thinmam/chromoly.py
thinmam/gap.py
thinmam/glass.py
thinmam.egg-info/PKG-INFO
thinmam.egg-info/SOURCES.txt
thinmam.egg-info/dependency_links.txt
thinmam.egg-info/top_level.txt