Metadata-Version: 2.1
Name: thinmam
Version: 0.0.3
Summary: Solid thermodynamic and mechanical properties package
Home-page: https://github.com/VikramGovindarajan/thinmam
Author: VikramGovindarajan
Author-email: vickymailbuddy@gmail.com
Project-URL: Bug Tracker, https://github.com/VikramGovindarajan/thinmam/issues
Classifier: Programming Language :: Python :: 3
Classifier: Operating System :: OS Independent
Requires-Python: >=3.6
